a2y/__init__.py
a2y-0.8.0.dist-info/LICENSE
a2y-0.8.0.dist-info/METADATA
a2y-0.8.0.dist-info/WHEEL
a2y-0.8.0.dist-info/top_level.txt
a2y-0.8.0.dist-info/RECORD
