Metadata-Version: 2.1
Name: a2y
Version: 0.8.0
Summary: A handy package for installing a2y series modules.
Home-page: http://www.sorobust.com/a2y/a2y.html
Author: Yu Han
Author-email: hanjunyu@163.com
License: Private
Platform: Windows
Platform: Linux
Classifier: Development Status :: 4 - Beta
Classifier: Intended Audience :: Developers
Classifier: License :: Free For Educational Use
Classifier: Programming Language :: Python :: 3.5
Classifier: Operating System :: Microsoft :: Windows :: Windows 10
Classifier: Operating System :: POSIX :: Linux
Requires-Dist: a2y-mew
Requires-Dist: a2y-testparameters
Requires-Dist: a2y-modbus
Requires-Dist: a2y-atsui
Requires-Dist: a2y-ats
Requires-Dist: a2y-touchui
Requires-Dist: a2y-touch
Requires-Dist: a2y-wxtools
